codepack/__init__.py
codepack/arg.py
codepack/argpack.py
codepack/code.py
codepack/codepack.py
codepack/base/__init__.py
codepack/base/code_base.py
codepack/base/codepack_base.py
codepack/base/function.py
codepack/interfaces/__init__.py
codepack/interfaces/docker.py
codepack/interfaces/dynamodb.py
codepack/interfaces/interface.py
codepack/interfaces/kafka_consumer.py
codepack/interfaces/kafka_producer.py
codepack/interfaces/mongodb.py
codepack/interfaces/mssql.py
codepack/interfaces/mysql.py
codepack/interfaces/oracledb.py
codepack/interfaces/s3.py
codepack/interfaces/sql_interface.py
codepack/plugins/__init__.py
codepack/plugins/callback.py
codepack/plugins/delivery.py
codepack/plugins/delivery_service.py
codepack/plugins/dependency.py
codepack/plugins/dependency_bag.py
codepack/plugins/dependency_monitor.py
codepack/plugins/docker_manager.py
codepack/plugins/employee.py
codepack/plugins/interpreter_manager.py
codepack/plugins/jobstore.py
codepack/plugins/manager.py
codepack/plugins/scheduler.py
codepack/plugins/service.py
codepack/plugins/snapshot_service.py
codepack/plugins/state.py
codepack/plugins/storable_job.py
codepack/plugins/storage_service.py
codepack/plugins/supervisor.py
codepack/plugins/worker.py
codepack/plugins/snapshots/__init__.py
codepack/plugins/snapshots/code_snapshot.py
codepack/plugins/snapshots/codepack_snapshot.py
codepack/plugins/snapshots/snapshot.py
codepack/plugins/snapshots/snapshotable.py
codepack/storages/__init__.py
codepack/storages/file_storage.py
codepack/storages/kafka_messenger.py
codepack/storages/memory_messenger.py
codepack/storages/memory_storage.py
codepack/storages/messenger.py
codepack/storages/mongo_storage.py
codepack/storages/s3_storage.py
codepack/storages/storable.py
codepack/storages/storage.py
codepack/utils/__init__.py
codepack/utils/common.py
codepack/utils/exceptions.py
codepack/utils/functions.py
codepack/utils/looper.py
codepack/utils/config/__init__.py
codepack/utils/config/alias.py
codepack-0.8.0.dist-info/LICENSE
codepack-0.8.0.dist-info/METADATA
codepack-0.8.0.dist-info/WHEEL
codepack-0.8.0.dist-info/top_level.txt
codepack-0.8.0.dist-info/RECORD
