Metadata-Version: 2.1
Name: codepack
Version: 0.8.0
Summary: CodePack is the package to easily make, run, and manage workflows
Home-page: https://github.com/ihnokim/codepack
Author: ihnokim
Author-email: ihnokim58@gmail.com
License: UNKNOWN
Keywords: codepack,workflow,pipeline
Platform: UNKNOWN
Classifier: Programming Language :: Python
Classifier: Programming Language :: Python :: 3
Classifier: Programming Language :: Python :: 3 :: Only
Classifier: Programming Language :: Python :: 3.6
Classifier: Programming Language :: Python :: 3.7
Classifier: Programming Language :: Python :: 3.8
Classifier: Programming Language :: Python :: 3.9
Classifier: License :: OSI Approved :: MIT License
Classifier: Operating System :: OS Independent
Requires-Python: >=3.6
Requires-Dist: dill (==0.3.4)
Requires-Dist: parse (==1.19.0)
Requires-Dist: requests (==2.26.0)
Requires-Dist: pyreadline
Requires-Dist: pymongo (==3.12.1)
Provides-Extra: all
Requires-Dist: sshtunnel (==0.4.0) ; extra == 'all'
Requires-Dist: PyMySQL (==1.0.2) ; extra == 'all'
Requires-Dist: pymssql (==2.2.2) ; extra == 'all'
Requires-Dist: boto3 (==1.19.6) ; extra == 'all'
Requires-Dist: cx-Oracle (==8.2.1) ; extra == 'all'
Requires-Dist: APScheduler (==3.8.1) ; extra == 'all'
Requires-Dist: kafka-python (==2.0.2) ; extra == 'all'
Requires-Dist: docker (==5.0.3) ; extra == 'all'
Requires-Dist: numpy ; extra == 'all'
Requires-Dist: pandas ; extra == 'all'
